contrast/__init__.py
contrast/import_hook.py
contrast/policy_v2.py
contrast/version.py
contrast/agent/__init__.py
contrast/agent/agent_state.py
contrast/agent/asgi.py
contrast/agent/disable_reaction.py
contrast/agent/events.py
contrast/agent/exceptions.py
contrast/agent/exclusions.py
contrast/agent/framework.py
contrast/agent/heartbeat_thread.py
contrast/agent/metrics.py
contrast/agent/patch_controller.py
contrast/agent/reaction_processor.py
contrast/agent/request.py
contrast/agent/request_context.py
contrast/agent/request_state.py
contrast/agent/scope.py
contrast/agent/settings.py
contrast/agent/settings_threads.py
contrast/agent/sys_monitoring.py
contrast/agent/telemetry.py
contrast/agent/thread_watcher.py
contrast/agent/validator.py
contrast/agent/agent_lib/__init__.py
contrast/agent/agent_lib/input_tracing.py
contrast/agent/assess/__init__.py
contrast/agent/assess/adjusted_span.py
contrast/agent/assess/apply_trigger.py
contrast/agent/assess/assess_exceptions.py
contrast/agent/assess/contrast_event.py
contrast/agent/assess/preflight.py
contrast/agent/assess/properties.py
contrast/agent/assess/sampling.py
contrast/agent/assess/string_tracker.py
contrast/agent/assess/tag.py
contrast/agent/assess/truncate.py
contrast/agent/assess/utils.py
contrast/agent/assess/policy/__init__.py
contrast/agent/assess/policy/analysis.py
contrast/agent/assess/policy/deadzone_node.py
contrast/agent/assess/policy/patches.py
contrast/agent/assess/policy/preshift.py
contrast/agent/assess/policy/propagation_node.py
contrast/agent/assess/policy/propagation_policy.py
contrast/agent/assess/policy/source_node.py
contrast/agent/assess/policy/source_policy.py
contrast/agent/assess/policy/string_propagation.py
contrast/agent/assess/policy/trigger_policy.py
contrast/agent/assess/policy/propagators/__init__.py
contrast/agent/assess/policy/propagators/append_propagator.py
contrast/agent/assess/policy/propagators/base_propagator.py
contrast_agent-10.23.0.dist-info/METADATA
contrast_agent-10.23.0.dist-info/WHEEL
contrast_agent-10.23.0.dist-info/entry_points.txt
contrast_agent-10.23.0.dist-info/top_level.txt
contrast_agent-10.23.0.dist-info/RECORD
contrast_agent-10.23.0.dist-info/licenses/LICENSE.txt
